OROPtry/__init__.py
OROPtry-0.0.1.dist-info/LICENSE
OROPtry-0.0.1.dist-info/METADATA
OROPtry-0.0.1.dist-info/WHEEL
OROPtry-0.0.1.dist-info/top_level.txt
OROPtry-0.0.1.dist-info/RECORD
