Metadata-Version: 2.1
Name: OROPtry
Version: 0.0.1
Summary: example package
Author: sijinghua
Requires-Python: >=3.7
License-File: LICENSE
